clsa_data/__init__.py
clsa_data-0.1.0.dist-info/METADATA
clsa_data-0.1.0.dist-info/WHEEL
clsa_data-0.1.0.dist-info/top_level.txt
clsa_data-0.1.0.dist-info/RECORD
